vault/__init__.py
vault/vault_sdk.py
vault/utils/__init__.py
vault/utils/constants.py
vault/utils/vault_cache.py
vault/utils/vault_custom_cache.py
vault/utils/vault_exception.py
vault_sdk_gyan-0.0.5.dist-info/METADATA
vault_sdk_gyan-0.0.5.dist-info/WHEEL
vault_sdk_gyan-0.0.5.dist-info/top_level.txt
vault_sdk_gyan-0.0.5.dist-info/RECORD
