Metadata-Version: 2.4
Name: vault-sdk-gyan
Version: 0.0.5
Summary: Concentric Vault Python SDK
Home-page: https://bitbucket.org/concentricai/apputils
Author: K Sridhar
Author-email: sridhar@concentric.ai
Project-URL: Source, https://bitbucket.org/concentricai/apputils/src/main/vaultsdk/pythonSdk/
Project-URL: Bug Tracker, https://concentricai.atlassian.net/jira/software/c/projects/SW/boards/2/backlog
Classifier: Development Status :: 4 - Beta
Classifier: Intended Audience :: Developers
Classifier: Topic :: Software Development :: Libraries :: Python Modules
Classifier: Programming Language :: Python :: 3
Classifier: Programming Language :: Python :: 3.6
Classifier: Programming Language :: Python :: 3.7
Classifier: Programming Language :: Python :: 3.8
Classifier: Programming Language :: Python :: 3.9
Classifier: Programming Language :: Python :: 3.10
Classifier: Programming Language :: Python :: 3.11
Classifier: Operating System :: OS Independent
Requires-Python: >=3.7
Dynamic: author
Dynamic: author-email
Dynamic: classifier
Dynamic: description
Dynamic: description-content-type
Dynamic: home-page
Dynamic: project-url
Dynamic: requires-python
Dynamic: summary
